[{"1807_0": ["waist", "seams", "recycled", "interlock", "elastic", "colour", "fit", "elastane", "nylon", "smooth", "stretchy", "black", "supportive", "material", "tight"]}, {"1808_0": ["waist", "seams", "recycled", "interlock", "elastic", "colour", "fit", "elastane", "nylon", "smooth", "stretchy", "black", "supportive", "material", "tight"]}, {"1809_0": ["waist", "seams", "recycled", "interlock", "elastic", "colour", "fit", "elastane", "nylon", "smooth", "stretchy", "black", "supportive", "material", "tight"]}, {"1810_0": ["sleek", "fabric", "recycled", "colour", "waist", "interlock", "elastic", "high", "length", "rise", "fit", "black", "aeroready", "seams", "elastane", "minimal", "polyester", "pocket", "key", "tight"]}, {"1811_0": ["sleek", "fabric", "recycled", "colour", "waist", "interlock", "elastic", "high", "length", "rise", "fit", "black", "aeroready", "seams", "elastane", "minimal", "polyester", "pocket", "key", "tight"]}, {"1812_0": ["sleek", "fabric", "recycled", "colour", "waist", "interlock", "elastic", "high", "length", "rise", "fit", "black", "aeroready", "seams", "elastane", "minimal", "polyester", "pocket", "key", "tight"]}, {"1813_0": ["sleek", "fabric", "recycled", "colour", "waist", "interlock", "elastic", "high", "length", "rise", "fit", "black", "aeroready", "seams", "elastane", "minimal", "polyester", "pocket", "key", "tight"]}, {"1814_0": ["fabric", "recycled", "shape", "colour", "mesh", "waist", "technology", "interlock", "elastic", "sport", "high", "slick", "rise", "fit", "gusset", "black", "aeroready", "elastane", "support", "retention", "polyester", "pocket", "optimised", "tight"]}, {"1815_0": ["fabric", "recycled", "shape", "colour", "mesh", "waist", "technology", "interlock", "elastic", "sport", "high", "slick", "rise", "fit", "gusset", "black", "aeroready", "elastane", "support", "retention", "polyester", "pocket", "optimised", "tight"]}, {"1816_0": ["fabric", "recycled", "shape", "colour", "mesh", "waist", "technology", "interlock", "elastic", "sport", "high", "slick", "rise", "fit", "gusset", "black", "aeroready", "elastane", "support", "retention", "polyester", "pocket", "optimised", "tight"]}, {"1817_0": ["waist", "single", "elastic", "high", "colour", "fit", "elastane", "jersey", "black", "regular", "cotton", "rise"]}, {"1818_0": ["waist", "single", "elastic", "high", "colour", "fit", "elastane", "jersey", "black", "regular", "cotton", "rise"]}, {"1819_0": ["waist", "single", "elastic", "high", "colour", "fit", "elastane", "jersey", "black", "regular", "cotton", "rise"]}, {"1820_0": ["waist", "single", "elastic", "high", "colour", "fit", "elastane", "jersey", "black", "regular", "cotton", "rise"]}, {"1821_0": ["recycled", "colour", "drawcord", "waist", "inseam", "interlock", "elastic", "back", "reflective", "phone", "length", "fit", "black", "aeroready", "details", "elastane", "polyester", "pocket", "tight"]}, {"1822_0": ["recycled", "colour", "drawcord", "waist", "inseam", "interlock", "elastic", "back", "reflective", "phone", "length", "fit", "black", "aeroready", "details", "elastane", "polyester", "pocket", "tight"]}, {"1823_0": ["recycled", "colour", "drawcord", "waist", "inseam", "interlock", "elastic", "back", "reflective", "phone", "length", "fit", "black", "aeroready", "details", "elastane", "polyester", "pocket", "tight"]}, {"1824_0": ["waist", "single", "elastic", "colour", "fit", "elastane", "jersey", "black", "tight", "cotton"]}, {"1825_0": ["waist", "aeroready", "recycled", "interlock", "elastic", "details", "colour", "fit", "elastane", "leg", "pockets", "polyester", "pocket", "black", "drawcord", "phone", "tight"]}, {"1826_0": ["waist", "aeroready", "recycled", "interlock", "elastic", "details", "colour", "fit", "elastane", "leg", "pockets", "polyester", "pocket", "black", "drawcord", "phone", "tight"]}, {"1827_0": ["single", "leggings", "white", "colour", "fit", "elastane", "jersey", "black", "regular", "cotton"]}, {"1828_0": ["single", "leggings", "white", "colour", "fit", "elastane", "jersey", "black", "regular", "cotton"]}, {"1829_0": ["single", "leggings", "white", "colour", "fit", "elastane", "jersey", "black", "regular", "cotton"]}, {"1830_0": ["waist", "single", "white", "elastic", "colour", "fit", "elastane", "jersey", "black", "cotton"]}, {"1831_0": ["fabric", "rise", "recycled", "interlock", "side", "fit", "elastane", "nylon", "pockets", "polyester", "black", "tight", "stretch", "feel"]}, {"1832_0": ["fabric", "rise", "recycled", "interlock", "side", "fit", "elastane", "nylon", "pockets", "polyester", "black", "tight", "stretch", "feel"]}, {"1833_0": ["fabric", "rise", "recycled", "interlock", "side", "fit", "elastane", "nylon", "pockets", "polyester", "black", "tight", "stretch", "feel"]}, {"1834_0": ["fabric", "recycled", "muscles", "front", "mesh", "stretch", "waist", "panels", "interlock", "elastic", "energy", "fit", "techfit", "black", "pockets", "gripper", "elastane", "nylon", "ventilation", "tight"]}, {"1835_0": ["fabric", "recycled", "muscles", "front", "mesh", "stretch", "waist", "panels", "interlock", "elastic", "energy", "fit", "techfit", "black", "pockets", "gripper", "elastane", "nylon", "ventilation", "tight"]}, {"1836_0": ["fabric", "recycled", "muscles", "front", "mesh", "stretch", "waist", "panels", "interlock", "elastic", "energy", "fit", "techfit", "black", "pockets", "gripper", "elastane", "nylon", "ventilation", "tight"]}, {"1837_0": ["fabric", "recycled", "muscles", "colour", "zones", "mesh", "stretch", "waist", "panels", "interlock", "elastic", "fuchsia", "high", "energy", "rise", "fit", "techfit", "gripper", "details", "elastane", "nylon", "ventilation", "tight"]}, {"1838_0": ["fabric", "recycled", "muscles", "colour", "zones", "mesh", "stretch", "waist", "panels", "interlock", "elastic", "fuchsia", "high", "energy", "rise", "fit", "techfit", "gripper", "details", "elastane", "nylon", "ventilation", "tight"]}, {"1839_0": ["waist", "aeroready", "recycled", "interlock", "elastic", "muscles", "length", "fit", "elastane", "energy", "colour", "blue", "polyester", "techfit", "bliss", "tight"]}, {"1840_0": ["waist", "aeroready", "recycled", "interlock", "elastic", "muscles", "length", "fit", "elastane", "energy", "colour", "blue", "polyester", "techfit", "bliss", "tight"]}, {"1841_0": ["fabric", "recycled", "shape", "colour", "mesh", "waist", "technology", "interlock", "elastic", "strata", "sport", "high", "slick", "length", "rise", "fit", "clay", "aeroready", "elastane", "support", "retention", "polyester", "pocket", "optimised", "tight"]}, {"1842_0": ["fabric", "recycled", "shape", "colour", "mesh", "waist", "technology", "interlock", "elastic", "strata", "sport", "high", "slick", "length", "rise", "fit", "clay", "aeroready", "elastane", "support", "retention", "polyester", "pocket", "optimised", "tight"]}, {"1843_0": ["fabric", "recycled", "shape", "colour", "mesh", "waist", "technology", "interlock", "elastic", "strata", "sport", "high", "slick", "length", "rise", "fit", "clay", "aeroready", "elastane", "support", "retention", "polyester", "pocket", "optimised", "tight"]}, {"1844_0": ["fabric", "recycled", "shape", "colour", "mesh", "waist", "technology", "interlock", "elastic", "strata", "sport", "high", "slick", "length", "rise", "fit", "clay", "aeroready", "elastane", "support", "retention", "polyester", "pocket", "optimised", "tight"]}, {"1845_0": ["fabric", "recycled", "shape", "colour", "mesh", "waist", "technology", "interlock", "elastic", "strata", "sport", "high", "slick", "length", "rise", "fit", "clay", "aeroready", "elastane", "support", "retention", "polyester", "pocket", "optimised", "tight"]}, {"1846_0": ["fabric", "recycled", "shape", "colour", "mesh", "waist", "technology", "interlock", "elastic", "strata", "sport", "high", "slick", "length", "rise", "fit", "clay", "aeroready", "elastane", "support", "retention", "polyester", "pocket", "optimised", "tight"]}, {"1847_0": ["sleek", "fabric", "recycled", "side", "colour", "shiny", "stretch", "interlock", "high", "inserts", "rise", "silver", "fit", "pockets", "violet", "feel", "elastane", "polyester", "tight"]}, {"1848_0": ["sleek", "fabric", "recycled", "short", "colour", "drawcord", "waist", "interlock", "elastic", "back", "reflective", "phone", "length", "fit", "leg", "black", "aeroready", "pockets", "adiform", "details", "elastane", "polyester", "pocket", "tight"]}, {"1849_0": ["recycled", "muscles", "colour", "blue", "zones", "mesh", "waist", "panels", "interlock", "elastic", "high", "energy", "rise", "compression", "fit", "techfit", "aeroready", "dawn", "elastane", "polyester", "tight"]}, {"1850_0": ["waist", "white", "artwork", "recycled", "interlock", "elastic", "side", "cloud", "high", "colour", "fit", "elastane", "blue", "ice", "polyester", "marimekko", "tight", "rise"]}, {"1851_0": ["waist", "single", "white", "tint", "dash", "cloud", "elastic", "colour", "fit", "elastane", "jersey", "mid", "green", "tight", "cotton"]}, {"1852_0": ["waist", "single", "white", "tint", "dash", "cloud", "elastic", "colour", "fit", "elastane", "jersey", "mid", "green", "tight", "cotton"]}, {"1853_0": ["waist", "sleek", "fabric", "recycled", "interlock", "perforation", "details", "colour", "fit", "elastane", "nylon", "black", "supportive", "tight", "feel"]}, {"1854_0": ["waist", "fabric", "seams", "aeroready", "recycled", "interlock", "elastic", "sport", "fit", "elastane", "thigh", "polyester", "pocket", "black", "tight", "stretch"]}, {"1855_0": ["waist", "fabric", "seams", "aeroready", "recycled", "interlock", "elastic", "sport", "fit", "elastane", "thigh", "polyester", "pocket", "black", "tight", "stretch"]}, {"1856_0": ["waist", "fabric", "seams", "aeroready", "recycled", "interlock", "elastic", "sport", "fit", "elastane", "thigh", "polyester", "pocket", "black", "tight", "stretch"]}, {"1857_0": ["waist", "fabric", "seams", "aeroready", "recycled", "interlock", "elastic", "sport", "fit", "elastane", "thigh", "polyester", "pocket", "black", "tight", "stretch"]}, {"1858_0": ["fabric", "recycled", "colour", "taupe", "adisoft", "smooth", "mesh", "waist", "tint", "interlock", "elastic", "strata", "high", "rise", "breathable", "fit", "clay", "aeroready", "seams", "soft", "elastane", "ecru", "polyester", "pocket", "tight"]}, {"1859_0": ["waist", "cotton", "elastic", "viscose", "colour", "fit", "elastane", "rib", "black", "tight"]}, {"1860_0": ["waist", "seams", "aeroready", "recycled", "interlock", "elastic", "length", "colour", "fit", "elastane", "blue", "minimal", "polyester", "pocket", "fusion", "key", "tight"]}, {"1861_0": ["waist", "seams", "aeroready", "recycled", "interlock", "elastic", "length", "colour", "fit", "elastane", "blue", "minimal", "polyester", "pocket", "fusion", "key", "tight"]}, {"1862_0": ["waist", "seams", "fabric", "aeroready", "recycled", "interlock", "elastic", "soft", "strata", "colour", "olive", "fit", "elastane", "adisoft", "smooth", "polyester", "contour", "tight"]}, {"1863_0": ["waist", "seams", "fabric", "aeroready", "recycled", "interlock", "elastic", "soft", "strata", "colour", "olive", "fit", "elastane", "adisoft", "smooth", "polyester", "contour", "tight"]}, {"1864_0": ["fabric", "recycled", "colour", "internal", "drawcord", "stretch", "waist", "interlock", "back", "high", "phone", "rise", "breathable", "fit", "lightweight", "black", "reflectivity", "elastane", "polyester", "pocket", "supportive", "tight"]}, {"1865_0": ["waist", "fabric", "seams", "aeroready", "recycled", "interlock", "elastic", "sport", "length", "fit", "elastane", "thigh", "colour", "minimal", "polyester", "pocket", "black", "tight"]}, {"1866_0": ["waist", "fabric", "seams", "aeroready", "recycled", "interlock", "elastic", "sport", "length", "fit", "elastane", "thigh", "colour", "minimal", "polyester", "pocket", "black", "tight"]}, {"1867_0": ["waist", "fabric", "seams", "aeroready", "recycled", "interlock", "elastic", "sport", "length", "fit", "elastane", "thigh", "colour", "minimal", "polyester", "pocket", "black", "tight"]}, {"1868_0": ["waist", "sleek", "fabric", "aeroready", "recycled", "interlock", "elastic", "seams", "high", "colour", "fit", "elastane", "polyester", "pocket", "black", "key", "tight", "rise"]}, {"1869_0": ["waist", "sleek", "fabric", "aeroready", "recycled", "interlock", "elastic", "seams", "high", "colour", "fit", "elastane", "polyester", "pocket", "black", "key", "tight", "rise"]}, {"1870_0": ["sleek", "fabric", "recycled", "colour", "drawcord", "waist", "interlock", "elastic", "back", "phone", "length", "fit", "leg", "black", "aeroready", "pockets", "details", "elastane", "polyester", "pocket", "tight"]}, {"1871_0": ["sleek", "fabric", "recycled", "colour", "drawcord", "waist", "interlock", "elastic", "back", "phone", "length", "fit", "leg", "black", "aeroready", "pockets", "details", "elastane", "polyester", "pocket", "tight"]}, {"1872_0": ["fabric", "recycled", "colour", "green", "adisoft", "smooth", "skin", "waist", "interlock", "elastic", "inner", "length", "second", "silver", "fit", "aeroready", "soft", "feels", "elastane", "polyester", "pocket", "tight"]}, {"1873_0": ["fabric", "recycled", "colour", "green", "adisoft", "smooth", "skin", "waist", "interlock", "elastic", "inner", "length", "second", "silver", "fit", "aeroready", "soft", "feels", "elastane", "polyester", "pocket", "tight"]}, {"1874_0": ["fabric", "recycled", "colour", "green", "adisoft", "smooth", "skin", "waist", "interlock", "elastic", "inner", "length", "second", "silver", "fit", "aeroready", "soft", "feels", "elastane", "polyester", "pocket", "tight"]}, {"1875_0": ["waist", "single", "slim", "badge", "sport", "colour", "fit", "elastane", "jersey", "structure", "black", "cotton", "stretch"]}, {"1876_0": ["waist", "single", "slim", "badge", "sport", "colour", "fit", "elastane", "jersey", "structure", "black", "cotton", "stretch"]}, {"1877_0": ["waist", "single", "slim", "badge", "sport", "colour", "fit", "elastane", "jersey", "structure", "black", "cotton", "stretch"]}, {"1878_0": ["waist", "elastic", "colour", "fit", "elastane", "black", "regular", "cotton"]}, {"1879_0": ["recycled", "side", "colour", "minimum", "drawcord", "plastic", "waist", "zip", "interlock", "elastic", "high", "reflective", "zigzag", "rise", "ocean", "fit", "yarn", "black", "pockets", "total", "elastane", "polyester", "pocket", "parley", "material", "tight", "garment"]}, {"1880_0": ["fabric", "waist", "rise", "recycled", "interlock", "soft", "high", "colour", "fit", "elastane", "adisoft", "smooth", "polyester", "pocket", "black", "tight", "stretch"]}, {"1881_0": ["fabric", "waist", "rise", "recycled", "interlock", "soft", "high", "colour", "fit", "elastane", "adisoft", "smooth", "polyester", "pocket", "black", "tight", "stretch"]}, {"1882_0": ["fabric", "waist", "rise", "recycled", "interlock", "soft", "high", "colour", "fit", "elastane", "adisoft", "smooth", "polyester", "pocket", "black", "tight", "stretch"]}, {"1883_0": ["sleek", "recycled", "muscles", "colour", "zones", "protection", "mesh", "system", "waist", "compressive", "interlock", "elastic", "panels", "high", "energy", "rise", "compression", "fit", "techfit", "black", "aeroready", "feel", "elastane", "polyester", "tight"]}, {"1884_0": ["sleek", "fabric", "recycled", "colour", "shiny", "zones", "mesh", "waist", "brown", "panels", "interlock", "elastic", "high", "length", "rise", "fit", "aeroready", "feel", "elastane", "polyester", "tight"]}, {"1885_0": ["breathable", "aeroready", "recycled", "doubleknit", "rise", "high", "colour", "fit", "elastane", "polyester", "wonder", "material", "tight", "stretch"]}, {"1886_0": ["breathable", "aeroready", "recycled", "doubleknit", "rise", "high", "colour", "fit", "elastane", "polyester", "wonder", "material", "tight", "stretch"]}, {"1887_0": ["breathable", "aeroready", "recycled", "doubleknit", "rise", "high", "colour", "fit", "elastane", "polyester", "wonder", "material", "tight", "stretch"]}, {"1888_0": ["breathable", "aeroready", "recycled", "doubleknit", "rise", "high", "colour", "fit", "elastane", "polyester", "wonder", "material", "tight", "stretch"]}, {"1889_0": ["recycled", "doubleknit", "colour", "drawcord", "stretch", "waist", "high", "reflective", "inside", "rise", "wonder", "breathable", "fit", "aeroready", "elastane", "detail", "polyester", "pocket", "material", "tight"]}]