[{"1440_0": ["single", "loose", "colour", "blue", "fit", "jersey", "red", "dark", "balance", "product", "cotton", "mass", "system"]}, {"1441_0": ["polo", "recycled", "multicolor", "button", "loose", "colour", "fit", "polyester", "crop", "black", "collar", "front", "mesh"]}, {"1442_0": ["recycled", "loose", "colour", "fit", "elastane", "taupe", "polyester", "wonder"]}, {"1443_0": ["slim", "viscose", "round", "length", "knit", "fit", "elastane", "colour", "bright", "rib", "cotton"]}, {"1444_0": ["fabric", "recycled", "mauve", "hem", "colour", "front", "crewneck", "length", "grey", "lyocell", "fit", "crop", "regular", "aeroready", "putty", "single", "tie", "jersey", "polyester"]}, {"1445_0": ["fabric", "recycled", "mauve", "hem", "colour", "front", "crewneck", "length", "grey", "lyocell", "fit", "crop", "regular", "aeroready", "putty", "single", "tie", "jersey", "polyester"]}, {"1446_0": ["polo", "slim", "viscose", "length", "knit", "fit", "elastane", "colour", "blue", "dark", "rib", "collar", "open", "cotton"]}, {"1447_0": ["polo", "slim", "viscose", "length", "knit", "fit", "elastane", "colour", "blue", "dark", "rib", "collar", "open", "cotton"]}, {"1448_0": ["recycled", "interlock", "fit", "elastane", "detachable", "straps", "adjustable", "polyester", "black", "sides", "flat", "tight"]}, {"1449_0": ["fabric", "single", "white", "panel", "recycled", "soft", "racerback", "colour", "fit", "jersey", "stretchy", "polyester", "crewneck", "regular", "mesh", "aeroready"]}, {"1450_0": ["fabric", "single", "white", "panel", "recycled", "soft", "racerback", "colour", "fit", "jersey", "stretchy", "polyester", "crewneck", "regular", "mesh", "aeroready"]}, {"1451_0": ["fabric", "single", "product", "details", "colour", "fit", "jersey", "ink", "crewneck", "balance", "regular", "look", "cotton", "mass", "system"]}, {"1452_0": ["fabric", "single", "product", "details", "colour", "fit", "jersey", "ink", "crewneck", "balance", "regular", "look", "cotton", "mass", "system"]}, {"1453_0": ["single", "slim", "recycled", "halo", "colour", "freelift", "fit", "elastane", "jersey", "design", "blue", "polyester", "aeroready"]}, {"1454_0": ["single", "slim", "recycled", "halo", "colour", "freelift", "fit", "elastane", "jersey", "design", "blue", "polyester", "aeroready"]}, {"1455_0": ["single", "slim", "recycled", "halo", "colour", "freelift", "fit", "elastane", "jersey", "design", "blue", "polyester", "aeroready"]}, {"1456_0": ["single", "slim", "recycled", "halo", "colour", "freelift", "fit", "elastane", "jersey", "design", "blue", "polyester", "aeroready"]}, {"1457_0": ["fabric", "aeroready", "recycled", "interlock", "lucid", "round", "neckline", "colour", "fit", "elastane", "super", "lightweight", "polyester", "racer", "lemon", "tight"]}, {"1458_0": ["slim", "recycled", "doubleknit", "overlap", "adidas", "colour", "fit", "polyester", "crop", "black", "collar", "sportswear", "graphic"]}, {"1459_0": ["fabric", "recycled", "mauve", "side", "viscose", "details", "colour", "fit", "elastane", "slits", "minimum", "content", "rib", "stretchy", "renewable", "tight", "cotton", "putty"]}, {"1460_0": ["fabric", "recycled", "mauve", "side", "viscose", "details", "colour", "fit", "elastane", "slits", "minimum", "content", "rib", "stretchy", "renewable", "tight", "cotton", "putty"]}, {"1461_0": ["fabric", "recycled", "mauve", "side", "viscose", "details", "colour", "fit", "elastane", "slits", "minimum", "content", "rib", "stretchy", "renewable", "tight", "cotton", "putty"]}, {"1462_0": ["recycled", "gold", "colour", "fit", "elastane", "nylon", "square", "tricot", "tight", "bold"]}, {"1463_0": ["recycled", "gold", "colour", "fit", "elastane", "nylon", "square", "tricot", "tight", "bold"]}, {"1464_0": ["fabric", "recycled", "abrasion", "side", "colour", "points", "spark", "round", "neckline", "tape", "inner", "plain", "racerback", "fit", "semi", "regular", "aeroready", "seams", "details", "elastane", "polyester"]}, {"1465_0": ["fabric", "recycled", "abrasion", "side", "colour", "points", "spark", "round", "neckline", "tape", "inner", "plain", "racerback", "fit", "semi", "regular", "aeroready", "seams", "details", "elastane", "polyester"]}, {"1466_0": ["fabric", "recycled", "bottom", "spark", "elastic", "round", "reflective", "length", "grey", "fit", "semi", "band", "crop", "aeroready", "single", "details", "elastane", "jersey", "polyester", "tight"]}, {"1467_0": ["fabric", "recycled", "bottom", "spark", "elastic", "round", "reflective", "length", "grey", "fit", "semi", "band", "crop", "aeroready", "single", "details", "elastane", "jersey", "polyester", "tight"]}, {"1468_0": ["legend", "single", "slim", "short", "colour", "blue", "fit", "jersey", "crewneck", "ink", "sleeves", "cotton", "wonder"]}, {"1469_0": ["legend", "single", "slim", "short", "colour", "blue", "fit", "jersey", "crewneck", "ink", "sleeves", "cotton", "wonder"]}, {"1470_0": ["legend", "single", "slim", "short", "colour", "blue", "fit", "jersey", "crewneck", "ink", "sleeves", "cotton", "wonder"]}, {"1471_0": ["legend", "single", "slim", "short", "colour", "blue", "fit", "jersey", "crewneck", "ink", "sleeves", "cotton", "wonder"]}, {"1472_0": ["legend", "single", "slim", "short", "colour", "blue", "fit", "jersey", "crewneck", "ink", "sleeves", "cotton", "wonder"]}, {"1473_0": ["legend", "single", "slim", "short", "colour", "blue", "fit", "jersey", "crewneck", "ink", "sleeves", "cotton", "wonder"]}, {"1474_0": ["acetate", "recycled", "short", "details", "colour", "charcoal", "fit", "minimum", "airchill", "reflective", "content", "renewable", "polyester", "crewneck", "regular", "length"]}, {"1475_0": ["acetate", "recycled", "short", "details", "colour", "charcoal", "fit", "minimum", "airchill", "reflective", "content", "renewable", "polyester", "crewneck", "regular", "length"]}, {"1476_0": ["single", "recycled", "soft", "seamlines", "colour", "blue", "fit", "elastane", "jersey", "semi", "grey", "polyester", "crewneck", "feminine", "regular", "aeroready", "feel"]}, {"1477_0": ["single", "recycled", "soft", "seamlines", "colour", "blue", "fit", "elastane", "jersey", "semi", "grey", "polyester", "crewneck", "feminine", "regular", "aeroready", "feel"]}, {"1478_0": ["single", "loose", "tone", "colour", "fit", "jersey", "balance", "product", "violet", "cotton", "mass", "system"]}, {"1479_0": ["single", "loose", "tone", "colour", "fit", "jersey", "balance", "product", "violet", "cotton", "mass", "system"]}, {"1480_0": ["slim", "recycled", "panels", "back", "side", "details", "round", "fuchsia", "fit", "elastane", "reflective", "polyester", "piqu\u00e9", "mesh", "aeroready"]}, {"1481_0": ["slim", "recycled", "panels", "back", "side", "details", "round", "fuchsia", "fit", "elastane", "reflective", "polyester", "piqu\u00e9", "mesh", "aeroready"]}, {"1482_0": ["slim", "recycled", "panels", "back", "side", "details", "round", "fuchsia", "fit", "elastane", "reflective", "polyester", "piqu\u00e9", "mesh", "aeroready"]}, {"1483_0": ["slim", "recycled", "panels", "back", "side", "details", "round", "fuchsia", "fit", "elastane", "reflective", "polyester", "piqu\u00e9", "mesh", "aeroready"]}, {"1484_0": ["slim", "recycled", "panels", "back", "side", "details", "round", "fuchsia", "fit", "elastane", "reflective", "polyester", "piqu\u00e9", "mesh", "aeroready"]}, {"1485_0": ["single", "slim", "wrapping", "badge", "round", "sport", "colour", "fit", "elastane", "jersey", "tape", "black", "balance", "product", "cotton", "mass", "system"]}, {"1486_0": ["single", "white", "short", "colour", "fit", "jersey", "initiative", "dark", "crewneck", "regular", "sleeves", "cotton", "grey"]}, {"1487_0": ["single", "white", "short", "colour", "fit", "jersey", "initiative", "dark", "crewneck", "regular", "sleeves", "cotton", "grey"]}, {"1488_0": ["single", "white", "short", "colour", "fit", "jersey", "initiative", "dark", "crewneck", "regular", "sleeves", "cotton", "grey"]}, {"1489_0": ["single", "white", "short", "colour", "fit", "jersey", "initiative", "dark", "crewneck", "regular", "sleeves", "cotton", "grey"]}, {"1490_0": ["fabric", "recycled", "colour", "green", "ingredient", "mesh", "technology", "linen", "reflective", "crewneck", "active", "silver", "fit", "chloride", "regular", "aeroready", "details", "elastane", "polyester"]}, {"1491_0": ["fabric", "recycled", "colour", "green", "ingredient", "mesh", "technology", "linen", "reflective", "crewneck", "active", "silver", "fit", "chloride", "regular", "aeroready", "details", "elastane", "polyester"]}, {"1492_0": ["fabric", "recycled", "colour", "green", "ingredient", "mesh", "technology", "linen", "reflective", "crewneck", "active", "silver", "fit", "chloride", "regular", "aeroready", "details", "elastane", "polyester"]}, {"1493_0": ["fabric", "recycled", "colour", "green", "ingredient", "mesh", "technology", "linen", "reflective", "crewneck", "active", "silver", "fit", "chloride", "regular", "aeroready", "details", "elastane", "polyester"]}, {"1494_0": ["fabric", "recycled", "doubleknit", "colour", "fit", "mock", "polyester", "black", "regular", "aeroready"]}, {"1495_0": ["fabric", "recycled", "doubleknit", "colour", "fit", "mock", "polyester", "black", "regular", "aeroready"]}, {"1496_0": ["fabric", "recycled", "doubleknit", "colour", "fit", "mock", "polyester", "black", "regular", "aeroready"]}, {"1497_0": ["fabric", "recycled", "side", "hem", "colour", "minimum", "collar", "twistknit", "stretch", "spark", "interlock", "polo", "vents", "fit", "lightweight", "semi", "renewable", "ribbed", "regular", "polyester", "content"]}, {"1498_0": ["white", "recycled", "details", "adidas", "colour", "jacquard", "fit", "mock", "polyester", "black", "regular", "primeknit"]}, {"1499_0": ["polo", "single", "breathable", "vents", "recycled", "fabric", "jade", "side", "hem", "colour", "crystal", "fit", "elastane", "jersey", "polyester", "collar", "regular", "stretch"]}, {"1500_0": ["polo", "single", "breathable", "vents", "recycled", "fabric", "jade", "side", "hem", "colour", "crystal", "fit", "elastane", "jersey", "polyester", "collar", "regular", "stretch"]}, {"1501_0": ["polo", "single", "breathable", "vents", "recycled", "fabric", "jade", "side", "hem", "colour", "crystal", "fit", "elastane", "jersey", "polyester", "collar", "regular", "stretch"]}, {"1502_0": ["single", "product", "adidas", "colour", "fit", "jersey", "ink", "crewneck", "balance", "regular", "sportswear", "graphic", "armholes", "cotton", "mass", "system"]}, {"1503_0": ["fabric", "recycled", "doubleknit", "soft", "hem", "colour", "charcoal", "fit", "polyester", "crewneck", "regular", "feel", "dry"]}, {"1504_0": ["fabric", "recycled", "doubleknit", "soft", "hem", "colour", "charcoal", "fit", "polyester", "crewneck", "regular", "feel", "dry"]}, {"1505_0": ["fabric", "zip", "aeroready", "recycled", "doubleknit", "back", "putty", "loose", "mauve", "colour", "fit", "minimum", "boat", "renewable", "polyester", "content", "cotton", "neck"]}, {"1506_0": ["single", "loose", "colour", "fit", "jersey", "black", "balance", "product", "graphic", "cotton", "mass", "system"]}, {"1507_0": ["spark", "recycled", "doubleknit", "soft", "details", "colour", "fit", "green", "reflective", "semi", "polyester", "crewneck", "regular", "racer", "feel", "dry"]}, {"1508_0": ["single", "recycled", "viscose", "halo", "colour", "freelift", "fit", "jersey", "blue", "design", "polyester", "crewneck", "regular", "aeroready"]}, {"1509_0": ["single", "recycled", "viscose", "halo", "colour", "freelift", "fit", "jersey", "blue", "design", "polyester", "crewneck", "regular", "aeroready"]}, {"1510_0": ["single", "recycled", "viscose", "halo", "colour", "freelift", "fit", "jersey", "blue", "design", "polyester", "crewneck", "regular", "aeroready"]}, {"1511_0": ["single", "recycled", "viscose", "halo", "colour", "freelift", "fit", "jersey", "blue", "design", "polyester", "crewneck", "regular", "aeroready"]}, {"1512_0": ["single", "recycled", "viscose", "halo", "colour", "freelift", "fit", "jersey", "blue", "design", "polyester", "crewneck", "regular", "aeroready"]}, {"1513_0": ["single", "recycled", "viscose", "halo", "colour", "freelift", "fit", "jersey", "blue", "design", "polyester", "crewneck", "regular", "aeroready"]}, {"1514_0": ["single", "recycled", "viscose", "halo", "colour", "freelift", "fit", "jersey", "blue", "design", "polyester", "crewneck", "regular", "aeroready"]}, {"1515_0": ["white", "recycled", "cloud", "loose", "colour", "knit", "fit", "elastane", "print", "minimum", "rib", "renewable", "crewneck", "content", "cotton"]}, {"1516_0": ["single", "slim", "colour", "blue", "fit", "elastane", "jersey", "cuffs", "crewneck", "balance", "product", "cotton", "mass", "system"]}, {"1517_0": ["single", "slim", "white", "colour", "fit", "elastane", "jersey", "cuffs", "crewneck", "balance", "product", "cotton", "mass", "system"]}, {"1518_0": ["single", "white", "recycled", "loose", "modal", "colour", "fit", "elastane", "jersey", "polyester"]}, {"1519_0": ["single", "white", "recycled", "loose", "colour", "fit", "jersey", "minimum", "renewable", "polyester", "content", "cotton"]}, {"1520_0": ["single", "white", "recycled", "loose", "colour", "fit", "jersey", "minimum", "renewable", "polyester", "content", "cotton"]}, {"1521_0": ["single", "white", "recycled", "loose", "colour", "fit", "jersey", "minimum", "renewable", "polyester", "content", "cotton"]}, {"1522_0": ["product", "colour", "knit", "fit", "elastane", "blue", "rib", "bird", "crewneck", "balance", "regular", "cotton", "mass", "system"]}, {"1523_0": ["fabric", "single", "factor", "recycled", "ultraviolet", "hem", "colour", "fit", "elastane", "jersey", "mock", "polyester", "protect", "upf", "regular", "ink", "cotton", "stretch"]}, {"1524_0": ["single", "recycled", "viscose", "colour", "fit", "jersey", "bright", "red", "polyester", "crewneck", "mel", "regular", "cotton"]}, {"1525_0": ["single", "recycled", "viscose", "colour", "fit", "jersey", "bright", "red", "polyester", "crewneck", "mel", "regular", "cotton"]}, {"1526_0": ["single", "recycled", "viscose", "colour", "fit", "jersey", "bright", "red", "polyester", "crewneck", "mel", "regular", "cotton"]}, {"1527_0": ["single", "white", "recycled", "mauve", "colour", "freelift", "fit", "elastane", "jersey", "design", "polyester", "crewneck", "regular", "aeroready", "putty"]}, {"1528_0": ["single", "white", "recycled", "mauve", "colour", "freelift", "fit", "elastane", "jersey", "design", "polyester", "crewneck", "regular", "aeroready", "putty"]}, {"1529_0": ["single", "white", "recycled", "mauve", "colour", "freelift", "fit", "elastane", "jersey", "design", "polyester", "crewneck", "regular", "aeroready", "putty"]}, {"1530_0": ["single", "white", "recycled", "mauve", "colour", "freelift", "fit", "elastane", "jersey", "design", "polyester", "crewneck", "regular", "aeroready", "putty"]}, {"1531_0": ["single", "white", "recycled", "mauve", "colour", "freelift", "fit", "elastane", "jersey", "design", "polyester", "crewneck", "regular", "aeroready", "putty"]}, {"1532_0": ["single", "white", "recycled", "mauve", "colour", "freelift", "fit", "elastane", "jersey", "design", "polyester", "crewneck", "regular", "aeroready", "putty"]}, {"1533_0": ["single", "white", "recycled", "mauve", "colour", "freelift", "fit", "elastane", "jersey", "design", "polyester", "crewneck", "regular", "aeroready", "putty"]}, {"1534_0": ["single", "white", "recycled", "mauve", "colour", "freelift", "fit", "elastane", "jersey", "design", "polyester", "crewneck", "regular", "aeroready", "putty"]}, {"1535_0": ["single", "slim", "white", "colour", "fit", "elastane", "jersey", "deep", "balance", "product", "cotton", "mass", "system"]}, {"1536_0": ["single", "slim", "white", "colour", "fit", "elastane", "jersey", "deep", "balance", "product", "cotton", "mass", "system"]}, {"1537_0": ["single", "slim", "white", "colour", "fit", "elastane", "jersey", "deep", "balance", "product", "cotton", "mass", "system"]}, {"1538_0": ["fold", "white", "pique", "hem", "colour", "fit", "collar", "regular", "cotton"]}, {"1539_0": ["single", "white", "recycled", "bomber", "length", "colour", "fit", "elastane", "jersey", "polyester", "black", "crewneck", "regular", "aeroready"]}, {"1540_0": ["fabric", "aeroready", "recycled", "interlock", "soft", "high", "colour", "fit", "elastane", "adisoft", "smooth", "polyester", "crop", "black", "tight"]}, {"1541_0": ["fabric", "aeroready", "recycled", "interlock", "soft", "high", "colour", "fit", "elastane", "adisoft", "smooth", "polyester", "crop", "black", "tight"]}, {"1542_0": ["zip", "aeroready", "recycled", "doubleknit", "half", "silver", "colour", "fit", "elastane", "polyester", "ribbed", "cuffs", "collar", "tight", "wonder"]}, {"1543_0": ["slim", "viscose", "colour", "fit", "elastane", "rib", "black", "cotton", "x"]}, {"1544_0": ["slim", "viscose", "colour", "fit", "elastane", "rib", "black", "cotton", "x"]}, {"1545_0": ["slim", "viscose", "colour", "fit", "elastane", "heather", "rib", "crewneck", "medium", "cotton", "grey", "x"]}, {"1546_0": ["slim", "viscose", "colour", "fit", "elastane", "heather", "rib", "crewneck", "medium", "cotton", "grey", "x"]}, {"1547_0": ["single", "colour", "fit", "jersey", "crewneck", "regular", "cotton", "grey"]}, {"1548_0": ["single", "colour", "elastane", "jersey", "cotton", "grey"]}, {"1549_0": ["slim", "viscose", "hem", "colour", "fit", "elastane", "rib", "black", "crewneck", "cotton", "x"]}, {"1550_0": ["slim", "viscose", "hem", "colour", "fit", "elastane", "rib", "black", "crewneck", "cotton", "x"]}, {"1551_0": ["single", "slim", "linen", "length", "colour", "fit", "elastane", "jersey", "green", "crewneck", "cotton"]}, {"1552_0": ["single", "slim", "linen", "length", "colour", "fit", "elastane", "jersey", "green", "crewneck", "cotton"]}, {"1553_0": ["aeroready", "recycled", "graphics", "side", "hem", "colour", "fit", "mock", "polyester", "regular", "piqu\u00e9", "cotton", "grey"]}, {"1554_0": ["single", "white", "recycled", "side", "hem", "colour", "freelift", "fit", "elastane", "jersey", "slits", "design", "shadow", "red", "polyester", "crewneck", "regular", "aeroready"]}, {"1555_0": ["single", "white", "recycled", "side", "hem", "colour", "freelift", "fit", "elastane", "jersey", "slits", "design", "shadow", "red", "polyester", "crewneck", "regular", "aeroready"]}, {"1556_0": ["single", "white", "recycled", "side", "hem", "colour", "freelift", "fit", "elastane", "jersey", "slits", "design", "shadow", "red", "polyester", "crewneck", "regular", "aeroready"]}, {"1557_0": ["single", "white", "recycled", "side", "hem", "colour", "freelift", "fit", "elastane", "jersey", "slits", "design", "shadow", "red", "polyester", "crewneck", "regular", "aeroready"]}, {"1558_0": ["aqua", "aeroready", "recycled", "interlock", "flash", "details", "reflective", "semi", "polyester", "graphic", "bar", "logo"]}, {"1559_0": ["fabric", "product", "reflectivity", "recycled", "colour", "fit", "minimum", "polyester", "version", "crewneck", "emissions", "black", "regular", "mesh", "aeroready", "previous"]}, {"1560_0": ["fabric", "product", "reflectivity", "recycled", "colour", "fit", "minimum", "polyester", "version", "crewneck", "emissions", "black", "regular", "mesh", "aeroready", "previous"]}, {"1561_0": ["fabric", "product", "reflectivity", "recycled", "colour", "fit", "minimum", "polyester", "version", "crewneck", "emissions", "black", "regular", "mesh", "aeroready", "previous"]}, {"1562_0": ["single", "slim", "white", "short", "colour", "fit", "jersey", "green", "crewneck", "sleeves", "cotton", "collegiate"]}, {"1563_0": ["single", "slim", "white", "short", "colour", "fit", "jersey", "green", "crewneck", "sleeves", "cotton", "collegiate"]}, {"1564_0": ["polo", "single", "fabric", "recycled", "colour", "fit", "elastane", "jersey", "polyester", "clay", "collar", "wonder", "regular", "bar", "stretch", "logo"]}, {"1565_0": ["polo", "single", "fabric", "recycled", "colour", "fit", "elastane", "jersey", "polyester", "clay", "collar", "wonder", "regular", "bar", "stretch", "logo"]}, {"1566_0": ["slim", "recycled", "twill", "multicolor", "colour", "fit", "elastane", "rib", "polyester", "front", "cotton"]}, {"1567_0": ["single", "slim", "white", "round", "colour", "fit", "elastane", "jersey", "cotton"]}, {"1568_0": ["slim", "recycled", "adidas", "colour", "fit", "scarlet", "polyester", "ribbed", "collar", "tricot", "graphic"]}, {"1569_0": ["fabric", "recycled", "colour", "waist", "white", "elastic", "shoulder", "french", "construction", "crewneck", "inner", "cotton", "racerback", "fit", "stretchy", "crop", "black", "regular", "aeroready", "seams", "soft", "elastane", "polyester", "terry"]}, {"1570_0": ["fabric", "recycled", "colour", "waist", "white", "elastic", "shoulder", "french", "construction", "crewneck", "inner", "cotton", "racerback", "fit", "stretchy", "crop", "black", "regular", "aeroready", "seams", "soft", "elastane", "polyester", "terry"]}, {"1571_0": ["fabric", "recycled", "colour", "waist", "white", "elastic", "shoulder", "french", "construction", "crewneck", "inner", "cotton", "racerback", "fit", "stretchy", "crop", "black", "regular", "aeroready", "seams", "soft", "elastane", "polyester", "terry"]}, {"1572_0": ["fabric", "recycled", "colour", "waist", "white", "elastic", "shoulder", "french", "construction", "crewneck", "inner", "cotton", "racerback", "fit", "stretchy", "crop", "black", "regular", "aeroready", "seams", "soft", "elastane", "polyester", "terry"]}, {"1573_0": ["fabric", "recycled", "colour", "front", "white", "elastic", "linen", "round", "large", "lyocell", "fit", "regular", "aeroready", "single", "seams", "soft", "jersey", "detail", "polyester", "armholes"]}, {"1574_0": ["fabric", "recycled", "colour", "front", "white", "elastic", "linen", "round", "large", "lyocell", "fit", "regular", "aeroready", "single", "seams", "soft", "jersey", "detail", "polyester", "armholes"]}, {"1575_0": ["white", "doubleknit", "sleeve", "colour", "fit", "contrast", "mock", "polyester", "regular", "bar", "logo"]}, {"1576_0": ["white", "recycled", "colour", "elastane", "polyester", "black", "collar", "mesh"]}, {"1577_0": ["single", "multicolor", "colour", "fit", "elastane", "jersey", "gold", "tight", "cotton", "bold"]}, {"1578_0": ["single", "tie", "crew", "colour", "fit", "elastane", "jersey", "yellow", "closure", "tight", "cotton"]}, {"1579_0": ["single", "hem", "colour", "fit", "elastane", "jersey", "black", "lace", "cotton", "relaxed"]}, {"1580_0": ["single", "hem", "colour", "fit", "elastane", "jersey", "black", "lace", "cotton", "relaxed"]}, {"1581_0": ["polo", "graphics", "loose", "pink", "colour", "fit", "black", "collar", "fusion", "piqu\u00e9", "cotton"]}, {"1582_0": ["recycled", "loose", "round", "colour", "crew", "fit", "yellow", "polyester", "tricot", "length"]}, {"1583_0": ["coral", "single", "hem", "colour", "elastane", "jersey", "semi", "glow", "crop", "real", "cotton"]}]