[{"1807_0": ["smooth", "black", "waist", "tight", "supportive", "interlock", "material", "nylon", "fit", "recycled", "elastic", "stretchy", "seams", "colour", "elastane"]}, {"1808_0": ["smooth", "black", "waist", "tight", "supportive", "interlock", "material", "nylon", "fit", "recycled", "elastic", "stretchy", "seams", "colour", "elastane"]}, {"1809_0": ["smooth", "black", "waist", "tight", "supportive", "interlock", "material", "nylon", "fit", "recycled", "elastic", "stretchy", "seams", "colour", "elastane"]}, {"1810_0": ["black", "tight", "length", "high", "seams", "elastane", "minimal", "interlock", "fit", "recycled", "sleek", "fabric", "polyester", "aeroready", "pocket", "waist", "key", "rise", "elastic", "colour"]}, {"1811_0": ["black", "tight", "length", "high", "seams", "elastane", "minimal", "interlock", "fit", "recycled", "sleek", "fabric", "polyester", "aeroready", "pocket", "waist", "key", "rise", "elastic", "colour"]}, {"1812_0": ["black", "tight", "length", "high", "seams", "elastane", "minimal", "interlock", "fit", "recycled", "sleek", "fabric", "polyester", "aeroready", "pocket", "waist", "key", "rise", "elastic", "colour"]}, {"1813_0": ["black", "tight", "length", "high", "seams", "elastane", "minimal", "interlock", "fit", "recycled", "sleek", "fabric", "polyester", "aeroready", "pocket", "waist", "key", "rise", "elastic", "colour"]}, {"1814_0": ["black", "tight", "high", "elastane", "support", "interlock", "fit", "recycled", "mesh", "fabric", "polyester", "technology", "aeroready", "shape", "pocket", "waist", "optimised", "retention", "rise", "gusset", "slick", "elastic", "sport", "colour"]}, {"1815_0": ["black", "tight", "high", "elastane", "support", "interlock", "fit", "recycled", "mesh", "fabric", "polyester", "technology", "aeroready", "shape", "pocket", "waist", "optimised", "retention", "rise", "gusset", "slick", "elastic", "sport", "colour"]}, {"1816_0": ["black", "tight", "high", "elastane", "support", "interlock", "fit", "recycled", "mesh", "fabric", "polyester", "technology", "aeroready", "shape", "pocket", "waist", "optimised", "retention", "rise", "gusset", "slick", "elastic", "sport", "colour"]}, {"1817_0": ["jersey", "regular", "single", "black", "waist", "high", "cotton", "fit", "rise", "elastic", "colour", "elastane"]}, {"1818_0": ["jersey", "regular", "single", "black", "waist", "high", "cotton", "fit", "rise", "elastic", "colour", "elastane"]}, {"1819_0": ["jersey", "regular", "single", "black", "waist", "high", "cotton", "fit", "rise", "elastic", "colour", "elastane"]}, {"1820_0": ["jersey", "regular", "single", "black", "waist", "high", "cotton", "fit", "rise", "elastic", "colour", "elastane"]}, {"1821_0": ["black", "tight", "length", "details", "inseam", "drawcord", "elastane", "reflective", "interlock", "fit", "recycled", "back", "phone", "polyester", "aeroready", "pocket", "waist", "elastic", "colour"]}, {"1822_0": ["black", "tight", "length", "details", "inseam", "drawcord", "elastane", "reflective", "interlock", "fit", "recycled", "back", "phone", "polyester", "aeroready", "pocket", "waist", "elastic", "colour"]}, {"1823_0": ["black", "tight", "length", "details", "inseam", "drawcord", "elastane", "reflective", "interlock", "fit", "recycled", "back", "phone", "polyester", "aeroready", "pocket", "waist", "elastic", "colour"]}, {"1824_0": ["jersey", "single", "black", "waist", "tight", "cotton", "fit", "elastic", "colour", "elastane"]}, {"1825_0": ["polyester", "pocket", "black", "pockets", "waist", "tight", "interlock", "details", "fit", "recycled", "elastic", "phone", "drawcord", "colour", "elastane", "aeroready", "leg"]}, {"1826_0": ["polyester", "pocket", "black", "pockets", "waist", "tight", "interlock", "details", "fit", "recycled", "elastic", "phone", "drawcord", "colour", "elastane", "aeroready", "leg"]}, {"1827_0": ["jersey", "regular", "single", "black", "leggings", "white", "cotton", "fit", "colour", "elastane"]}, {"1828_0": ["jersey", "regular", "single", "black", "leggings", "white", "cotton", "fit", "colour", "elastane"]}, {"1829_0": ["jersey", "regular", "single", "black", "leggings", "white", "cotton", "fit", "colour", "elastane"]}, {"1830_0": ["jersey", "single", "black", "waist", "white", "cotton", "fit", "elastic", "colour", "elastane"]}, {"1831_0": ["polyester", "black", "tight", "interlock", "nylon", "fit", "feel", "recycled", "rise", "fabric", "stretch", "side", "elastane", "pockets"]}, {"1832_0": ["polyester", "black", "tight", "interlock", "nylon", "fit", "feel", "recycled", "rise", "fabric", "stretch", "side", "elastane", "pockets"]}, {"1833_0": ["polyester", "black", "tight", "interlock", "nylon", "fit", "feel", "recycled", "rise", "fabric", "stretch", "side", "elastane", "pockets"]}, {"1834_0": ["black", "tight", "energy", "elastane", "interlock", "front", "fit", "recycled", "mesh", "fabric", "stretch", "panels", "pockets", "techfit", "muscles", "gripper", "ventilation", "waist", "nylon", "elastic"]}, {"1835_0": ["black", "tight", "energy", "elastane", "interlock", "front", "fit", "recycled", "mesh", "fabric", "stretch", "panels", "pockets", "techfit", "muscles", "gripper", "ventilation", "waist", "nylon", "elastic"]}, {"1836_0": ["black", "tight", "energy", "elastane", "interlock", "front", "fit", "recycled", "mesh", "fabric", "stretch", "panels", "pockets", "techfit", "muscles", "gripper", "ventilation", "waist", "nylon", "elastic"]}, {"1837_0": ["tight", "high", "energy", "details", "elastane", "interlock", "fit", "recycled", "mesh", "fabric", "stretch", "panels", "techfit", "zones", "fuchsia", "muscles", "gripper", "ventilation", "waist", "nylon", "rise", "elastic", "colour"]}, {"1838_0": ["tight", "high", "energy", "details", "elastane", "interlock", "fit", "recycled", "mesh", "fabric", "stretch", "panels", "techfit", "zones", "fuchsia", "muscles", "gripper", "ventilation", "waist", "nylon", "rise", "elastic", "colour"]}, {"1839_0": ["polyester", "techfit", "waist", "tight", "length", "interlock", "muscles", "energy", "fit", "recycled", "elastic", "blue", "bliss", "colour", "elastane", "aeroready"]}, {"1840_0": ["polyester", "techfit", "waist", "tight", "length", "interlock", "muscles", "energy", "fit", "recycled", "elastic", "blue", "bliss", "colour", "elastane", "aeroready"]}, {"1841_0": ["tight", "length", "high", "clay", "strata", "elastane", "support", "interlock", "fit", "recycled", "mesh", "fabric", "polyester", "technology", "aeroready", "shape", "pocket", "waist", "optimised", "retention", "rise", "slick", "elastic", "sport", "colour"]}, {"1842_0": ["tight", "length", "high", "clay", "strata", "elastane", "support", "interlock", "fit", "recycled", "mesh", "fabric", "polyester", "technology", "aeroready", "shape", "pocket", "waist", "optimised", "retention", "rise", "slick", "elastic", "sport", "colour"]}, {"1843_0": ["tight", "length", "high", "clay", "strata", "elastane", "support", "interlock", "fit", "recycled", "mesh", "fabric", "polyester", "technology", "aeroready", "shape", "pocket", "waist", "optimised", "retention", "rise", "slick", "elastic", "sport", "colour"]}, {"1844_0": ["tight", "length", "high", "clay", "strata", "elastane", "support", "interlock", "fit", "recycled", "mesh", "fabric", "polyester", "technology", "aeroready", "shape", "pocket", "waist", "optimised", "retention", "rise", "slick", "elastic", "sport", "colour"]}, {"1845_0": ["tight", "length", "high", "clay", "strata", "elastane", "support", "interlock", "fit", "recycled", "mesh", "fabric", "polyester", "technology", "aeroready", "shape", "pocket", "waist", "optimised", "retention", "rise", "slick", "elastic", "sport", "colour"]}, {"1846_0": ["tight", "length", "high", "clay", "strata", "elastane", "support", "interlock", "fit", "recycled", "mesh", "fabric", "polyester", "technology", "aeroready", "shape", "pocket", "waist", "optimised", "retention", "rise", "slick", "elastic", "sport", "colour"]}, {"1847_0": ["shiny", "tight", "high", "side", "elastane", "silver", "violet", "interlock", "fit", "recycled", "sleek", "fabric", "stretch", "pockets", "polyester", "feel", "inserts", "rise", "colour"]}, {"1848_0": ["black", "tight", "length", "details", "drawcord", "elastane", "short", "reflective", "interlock", "fit", "recycled", "sleek", "back", "fabric", "phone", "pockets", "adiform", "polyester", "aeroready", "leg", "pocket", "waist", "elastic", "colour"]}, {"1849_0": ["tight", "high", "energy", "elastane", "dawn", "interlock", "fit", "recycled", "mesh", "panels", "polyester", "techfit", "zones", "muscles", "blue", "aeroready", "compression", "waist", "rise", "elastic", "colour"]}, {"1850_0": ["polyester", "waist", "tight", "artwork", "interlock", "high", "white", "fit", "rise", "recycled", "elastic", "ice", "marimekko", "colour", "blue", "side", "elastane", "cloud"]}, {"1851_0": ["jersey", "single", "waist", "tight", "green", "white", "cotton", "dash", "fit", "tint", "elastic", "colour", "elastane", "mid", "cloud"]}, {"1852_0": ["jersey", "single", "waist", "tight", "green", "white", "cotton", "dash", "fit", "tint", "elastic", "colour", "elastane", "mid", "cloud"]}, {"1853_0": ["black", "waist", "tight", "supportive", "interlock", "perforation", "details", "nylon", "fit", "feel", "recycled", "sleek", "fabric", "colour", "elastane"]}, {"1854_0": ["polyester", "pocket", "black", "waist", "tight", "interlock", "thigh", "fit", "recycled", "sport", "elastic", "fabric", "stretch", "seams", "elastane", "aeroready"]}, {"1855_0": ["polyester", "pocket", "black", "waist", "tight", "interlock", "thigh", "fit", "recycled", "sport", "elastic", "fabric", "stretch", "seams", "elastane", "aeroready"]}, {"1856_0": ["polyester", "pocket", "black", "waist", "tight", "interlock", "thigh", "fit", "recycled", "sport", "elastic", "fabric", "stretch", "seams", "elastane", "aeroready"]}, {"1857_0": ["polyester", "pocket", "black", "waist", "tight", "interlock", "thigh", "fit", "recycled", "sport", "elastic", "fabric", "stretch", "seams", "elastane", "aeroready"]}, {"1858_0": ["tight", "high", "clay", "seams", "strata", "elastane", "tint", "breathable", "interlock", "fit", "recycled", "mesh", "fabric", "taupe", "polyester", "aeroready", "smooth", "pocket", "waist", "adisoft", "rise", "elastic", "ecru", "colour", "soft"]}, {"1859_0": ["black", "waist", "tight", "cotton", "fit", "elastic", "colour", "elastane", "viscose", "rib"]}, {"1860_0": ["polyester", "pocket", "fusion", "waist", "tight", "minimal", "interlock", "key", "length", "fit", "recycled", "elastic", "seams", "blue", "colour", "elastane", "aeroready"]}, {"1861_0": ["polyester", "pocket", "fusion", "waist", "tight", "minimal", "interlock", "key", "length", "fit", "recycled", "elastic", "seams", "blue", "colour", "elastane", "aeroready"]}, {"1862_0": ["smooth", "polyester", "waist", "tight", "interlock", "adisoft", "soft", "fit", "recycled", "contour", "elastic", "seams", "fabric", "colour", "strata", "elastane", "aeroready", "olive"]}, {"1863_0": ["smooth", "polyester", "waist", "tight", "interlock", "adisoft", "soft", "fit", "recycled", "contour", "elastic", "seams", "fabric", "colour", "strata", "elastane", "aeroready", "olive"]}, {"1864_0": ["black", "tight", "high", "drawcord", "elastane", "breathable", "interlock", "reflectivity", "fit", "recycled", "back", "fabric", "stretch", "phone", "lightweight", "polyester", "internal", "pocket", "waist", "supportive", "rise", "colour"]}, {"1865_0": ["polyester", "pocket", "black", "waist", "tight", "minimal", "interlock", "thigh", "length", "fit", "recycled", "sport", "elastic", "fabric", "seams", "colour", "elastane", "aeroready"]}, {"1866_0": ["polyester", "pocket", "black", "waist", "tight", "minimal", "interlock", "thigh", "length", "fit", "recycled", "sport", "elastic", "fabric", "seams", "colour", "elastane", "aeroready"]}, {"1867_0": ["polyester", "pocket", "black", "waist", "tight", "minimal", "interlock", "thigh", "length", "fit", "recycled", "sport", "elastic", "fabric", "seams", "colour", "elastane", "aeroready"]}, {"1868_0": ["polyester", "pocket", "black", "waist", "tight", "interlock", "high", "key", "fit", "rise", "recycled", "sleek", "elastic", "fabric", "seams", "colour", "elastane", "aeroready"]}, {"1869_0": ["polyester", "pocket", "black", "waist", "tight", "interlock", "high", "key", "fit", "rise", "recycled", "sleek", "elastic", "fabric", "seams", "colour", "elastane", "aeroready"]}, {"1870_0": ["black", "tight", "length", "details", "drawcord", "elastane", "interlock", "fit", "recycled", "sleek", "back", "fabric", "phone", "pockets", "polyester", "aeroready", "leg", "pocket", "waist", "elastic", "colour"]}, {"1871_0": ["black", "tight", "length", "details", "drawcord", "elastane", "interlock", "fit", "recycled", "sleek", "back", "fabric", "phone", "pockets", "polyester", "aeroready", "leg", "pocket", "waist", "elastic", "colour"]}, {"1872_0": ["tight", "second", "length", "skin", "elastane", "silver", "interlock", "fit", "recycled", "fabric", "polyester", "green", "aeroready", "smooth", "pocket", "waist", "adisoft", "inner", "feels", "elastic", "colour", "soft"]}, {"1873_0": ["tight", "second", "length", "skin", "elastane", "silver", "interlock", "fit", "recycled", "fabric", "polyester", "green", "aeroready", "smooth", "pocket", "waist", "adisoft", "inner", "feels", "elastic", "colour", "soft"]}, {"1874_0": ["tight", "second", "length", "skin", "elastane", "silver", "interlock", "fit", "recycled", "fabric", "polyester", "green", "aeroready", "smooth", "pocket", "waist", "adisoft", "inner", "feels", "elastic", "colour", "soft"]}, {"1875_0": ["jersey", "structure", "slim", "single", "black", "waist", "cotton", "badge", "fit", "sport", "stretch", "colour", "elastane"]}, {"1876_0": ["jersey", "structure", "slim", "single", "black", "waist", "cotton", "badge", "fit", "sport", "stretch", "colour", "elastane"]}, {"1877_0": ["jersey", "structure", "slim", "single", "black", "waist", "cotton", "badge", "fit", "sport", "stretch", "colour", "elastane"]}, {"1878_0": ["regular", "black", "waist", "cotton", "fit", "elastic", "colour", "elastane"]}, {"1879_0": ["black", "tight", "high", "garment", "zip", "drawcord", "side", "elastane", "reflective", "ocean", "yarn", "parley", "interlock", "total", "fit", "recycled", "zigzag", "pockets", "polyester", "pocket", "plastic", "waist", "minimum", "material", "rise", "elastic", "colour"]}, {"1880_0": ["smooth", "polyester", "pocket", "black", "waist", "tight", "interlock", "adisoft", "high", "fit", "rise", "recycled", "fabric", "stretch", "colour", "elastane", "soft"]}, {"1881_0": ["smooth", "polyester", "pocket", "black", "waist", "tight", "interlock", "adisoft", "high", "fit", "rise", "recycled", "fabric", "stretch", "colour", "elastane", "soft"]}, {"1882_0": ["smooth", "polyester", "pocket", "black", "waist", "tight", "interlock", "adisoft", "high", "fit", "rise", "recycled", "fabric", "stretch", "colour", "elastane", "soft"]}, {"1883_0": ["black", "system", "tight", "high", "energy", "elastane", "interlock", "fit", "recycled", "sleek", "mesh", "compressive", "panels", "polyester", "techfit", "zones", "muscles", "feel", "protection", "aeroready", "compression", "waist", "rise", "elastic", "colour"]}, {"1884_0": ["shiny", "tight", "length", "high", "elastane", "interlock", "fit", "recycled", "sleek", "mesh", "fabric", "brown", "panels", "polyester", "zones", "feel", "aeroready", "waist", "rise", "elastic", "colour"]}, {"1885_0": ["polyester", "breathable", "material", "tight", "high", "fit", "rise", "recycled", "wonder", "stretch", "colour", "doubleknit", "elastane", "aeroready"]}, {"1886_0": ["polyester", "breathable", "material", "tight", "high", "fit", "rise", "recycled", "wonder", "stretch", "colour", "doubleknit", "elastane", "aeroready"]}, {"1887_0": ["polyester", "breathable", "material", "tight", "high", "fit", "rise", "recycled", "wonder", "stretch", "colour", "doubleknit", "elastane", "aeroready"]}, {"1888_0": ["polyester", "breathable", "material", "tight", "high", "fit", "rise", "recycled", "wonder", "stretch", "colour", "doubleknit", "elastane", "aeroready"]}, {"1889_0": ["tight", "high", "wonder", "drawcord", "doubleknit", "elastane", "reflective", "breathable", "inside", "fit", "recycled", "stretch", "polyester", "aeroready", "detail", "pocket", "waist", "material", "rise", "colour"]}, {"1890_0": ["tight", "high", "wonder", "drawcord", "doubleknit", "elastane", "reflective", "breathable", "inside", "fit", "recycled", "stretch", "polyester", "aeroready", "detail", "pocket", "waist", "material", "rise", "colour"]}, {"1891_0": ["black", "tight", "length", "high", "details", "seams", "elastane", "interlock", "fit", "recycled", "fabric", "polyester", "aeroready", "smooth", "waist", "adisoft", "rise", "elastic", "colour", "soft"]}, {"1892_0": ["polyester", "thebe", "magugu", "waist", "tight", "length", "interlock", "graphic", "pulse", "fit", "feel", "recycled", "elastic", "blue", "colour", "elastane", "aeroready"]}, {"1893_0": ["polyester", "thebe", "magugu", "waist", "tight", "length", "interlock", "graphic", "pulse", "fit", "feel", "recycled", "elastic", "blue", "colour", "elastane", "aeroready"]}, {"1894_0": ["jersey", "pocket", "single", "rush", "waist", "tight", "app", "cotton", "zip", "fit", "elastic", "colour", "initiative", "elastane", "sky", "leg"]}, {"1895_0": ["jersey", "single", "body", "shadow", "cotton", "nylon", "mesh", "colour", "lining", "initiative", "elastane", "navy"]}, {"1896_0": ["tight", "second", "skin", "elastane", "interlock", "fit", "recycled", "fabric", "grey", "polyester", "trace", "aeroready", "smooth", "pocket", "waist", "adisoft", "inner", "feels", "elastic", "colour", "soft"]}, {"1897_0": ["tight", "second", "skin", "elastane", "interlock", "fit", "recycled", "fabric", "grey", "polyester", "trace", "aeroready", "smooth", "pocket", "waist", "adisoft", "inner", "feels", "elastic", "colour", "soft"]}, {"1898_0": ["tight", "second", "skin", "seams", "doubleknit", "elastane", "fit", "recycled", "fabric", "grey", "polyester", "trace", "aeroready", "smooth", "waist", "nylon", "rise", "feels", "elastic", "colour", "soft"]}, {"1899_0": ["tight", "second", "skin", "seams", "doubleknit", "elastane", "fit", "recycled", "fabric", "grey", "polyester", "trace", "aeroready", "smooth", "waist", "nylon", "rise", "feels", "elastic", "colour", "soft"]}, {"1900_0": ["carbon", "tight", "length", "high", "semi", "seams", "elastane", "interlock", "fit", "recycled", "sleek", "polyester", "impact", "feel", "aeroready", "waist", "rise", "elastic", "colour", "orange"]}, {"1901_0": ["carbon", "tight", "length", "high", "semi", "seams", "elastane", "interlock", "fit", "recycled", "sleek", "polyester", "impact", "feel", "aeroready", "waist", "rise", "elastic", "colour", "orange"]}, {"1902_0": ["carbon", "tight", "length", "high", "semi", "seams", "elastane", "interlock", "fit", "recycled", "sleek", "polyester", "impact", "feel", "aeroready", "waist", "rise", "elastic", "colour", "orange"]}, {"1903_0": ["polyester", "waist", "tight", "lilac", "interlock", "yellow", "fit", "recycled", "elastic", "print", "bliss", "colour", "elastane"]}]